{
  "phase1": {
    "name": "Critical Blockers",
    "duration": "3 days",
    "planned": "4 weeks",
    "savings": "87.5%",
    "tests": 293,
    "status": "Complete"
  },
  "phase2": {
    "name": "Deployment & Reliability",
    "duration": "4 minutes",
    "planned": "5 days",
    "savings": "99.9%",
    "tests": 86,
    "status": "Complete"
  },
  "phase3": {
    "name": "Evidence Collection",
    "duration": "In Progress",
    "planned": "3 days",
    "tests": "TBD",
    "status": "In Progress"
  }
}